{
    "신사_신분당": {
        "id": "신사_신분당",
        "name": "신사",
        "line": "신분당선",
        "neighbors": [
            "논현_신분당",
            "신사_3"
        ]
    },
    "논현_신분당": {
        "id": "논현_신분당",
        "name": "논현",
        "line": "신분당선",
        "neighbors": [
            "신사_신분당",
            "신논현_신분당",
            "논현_7"
        ]
    },
    "신논현_신분당": {
        "id": "신논현_신분당",
        "name": "신논현",
        "line": "신분당선",
        "neighbors": [
            "논현_신분당",
            "강남_신분당",
            "신논현_9"
        ]
    },
    "강남_신분당": {
        "id": "강남_신분당",
        "name": "강남",
        "line": "신분당선",
        "neighbors": [
            "신논현_신분당",
            "양재_신분당",
            "강남_2"
        ]
    },
    "양재_신분당": {
        "id": "양재_신분당",
        "name": "양재",
        "line": "신분당선",
        "neighbors": [
            "강남_신분당",
            "양재시민의숲_신분당",
            "양재_3"
        ]
    },
    "양재시민의숲_신분당": {
        "id": "양재시민의숲_신분당",
        "name": "양재시민의숲",
        "line": "신분당선",
        "neighbors": [
            "양재_신분당",
            "청계산입구_신분당"
        ]
    },
    "청계산입구_신분당": {
        "id": "청계산입구_신분당",
        "name": "청계산입구",
        "line": "신분당선",
        "neighbors": [
            "양재시민의숲_신분당",
            "판교_신분당"
        ]
    },
    "판교_신분당": {
        "id": "판교_신분당",
        "name": "판교",
        "line": "신분당선",
        "neighbors": [
            "청계산입구_신분당",
            "정자_신분당"
        ]
    },
    "정자_신분당": {
        "id": "정자_신분당",
        "name": "정자",
        "line": "신분당선",
        "neighbors": [
            "판교_신분당",
            "미금_신분당",
            "정자_분당"
        ]
    },
    "미금_신분당": {
        "id": "미금_신분당",
        "name": "미금",
        "line": "신분당선",
        "neighbors": [
            "정자_신분당",
            "동천_신분당",
            "미금_분당"
        ]
    },
    "동천_신분당": {
        "id": "동천_신분당",
        "name": "동천",
        "line": "신분당선",
        "neighbors": [
            "미금_신분당",
            "수지구청_신분당"
        ]
    },
    "수지구청_신분당": {
        "id": "수지구청_신분당",
        "name": "수지구청",
        "line": "신분당선",
        "neighbors": [
            "동천_신분당",
            "성복_신분당"
        ]
    },
    "성복_신분당": {
        "id": "성복_신분당",
        "name": "성복",
        "line": "신분당선",
        "neighbors": [
            "수지구청_신분당",
            "상현_신분당"
        ]
    },
    "상현_신분당": {
        "id": "상현_신분당",
        "name": "상현",
        "line": "신분당선",
        "neighbors": [
            "성복_신분당",
            "광교중앙_신분당"
        ]
    },
    "광교중앙_신분당": {
        "id": "광교중앙_신분당",
        "name": "광교중앙",
        "line": "신분당선",
        "neighbors": [
            "상현_신분당",
            "광교_신분당"
        ]
    },
    "광교_신분당": {
        "id": "광교_신분당",
        "name": "광교",
        "line": "신분당선",
        "neighbors": [
            "광교중앙_신분당"
        ]
    }
}
